{
	"name": "Meta_Cons_Repair_Kit_Effectiveness_Background",
	"plugin-id": "Sprite",
	"sid": 365716315471569,
	"isGlobal": false,
	"editorNewInstanceIsReplica": true,
	"instanceVariables": [],
	"behaviorTypes": [
		{
			"behaviorId": "Pin",
			"name": "Pin",
			"sid": 871757830856782
		}
	],
	"effectTypes": [
		{
			"effectId": "darken",
			"name": "Darken"
		}
	],
	"animations": {
		"items": [
			{
				"frames": [
					{
						"width": 341,
						"height": 64,
						"originX": 0.501466275659824,
						"originY": 0.5,
						"originalSource": "",
						"exportFormat": "lossless",
						"exportQuality": 0.8,
						"fileType": "image/png",
						"imageSpriteId": 9332916,
						"collisionPoly": {
							"points": [
								0.003968253968253968,
								0.003968253968253968,
								0.996031746031746,
								0.003968253968253968,
								0.996031746031746,
								0.996031746031746,
								0.003968253968253968,
								0.996031746031746
							]
						},
						"useCollisionPoly": true,
						"duration": 1,
						"tag": ""
					}
				],
				"sid": 377766486347642,
				"name": "Background",
				"isLooping": false,
				"isPingPong": false,
				"repeatCount": 1,
				"repeatTo": 0,
				"speed": 5
			}
		],
		"subfolders": []
	}
}